searcher_py_async/__init__.py
searcher_py_async/api_client.py
searcher_py_async/api_response.py
searcher_py_async/configuration.py
searcher_py_async/exceptions.py
searcher_py_async/py.typed
searcher_py_async/rest.py
searcher_py_async/api/__init__.py
searcher_py_async/api/dict_api.py
searcher_py_async/api/embedding_api.py
searcher_py_async/api/policy_api.py
searcher_py_async/api/search_api.py
searcher_py_async/models/__init__.py
searcher_py_async/models/default_response_string_string.py
searcher_py_async/models/default_response_vec_f64_string.py
searcher_py_async/models/default_response_vec_search_detail_string.py
searcher_py_async/models/default_response_vec_search_detail_string_data_inner.py
searcher_py_async/models/index_dict.py
searcher_py_async/models/index_name.py
searcher_py_async/models/position_search_filter.py
searcher_py_async/models/related_similar_query.py
searcher_py_async/models/search_detail.py
searcher_py_async/models/search_request_body_position_search_filter.py
searcher_py_async/models/search_request_body_position_search_filter_filter.py
lipin_searcher_py_async-0.3.6.dist-info/METADATA
lipin_searcher_py_async-0.3.6.dist-info/WHEEL
lipin_searcher_py_async-0.3.6.dist-info/top_level.txt
lipin_searcher_py_async-0.3.6.dist-info/RECORD
