Metadata-Version: 2.1
Name: lipin-searcher-py-async
Version: 0.3.6
Summary: searcher
Home-page: 
Author: kaka
Author-email: kaka@cingta.com
License: searcher_license
Keywords: OpenAPI,OpenAPI-Generator,searcher
Requires-Dist: urllib3 <3.0.0,>=2.1.0
Requires-Dist: python-dateutil >=2.8.2
Requires-Dist: aiohttp >=3.8.4
Requires-Dist: aiohttp-retry >=2.8.3
Requires-Dist: pydantic >=2
Requires-Dist: typing-extensions >=4.7.1
